openapi/__init__.py
openapi/client.py
openapi/service.py
yjpainting_sdk-1.0.0.dist-info/METADATA
yjpainting_sdk-1.0.0.dist-info/WHEEL
yjpainting_sdk-1.0.0.dist-info/top_level.txt
yjpainting_sdk-1.0.0.dist-info/RECORD
